cratch/__about__.py
cratch/__init__.py
cratch/io/__init__.py
cratch/io/_format_csv.py
cratch/io/_format_fast.py
cratch/io/_format_off.py
cratch/io/_format_svg.py
cratch/io/_format_vtk.py
cratch/io/_format_vtu.py
cratch/mesh/__init__.py
cratch/mesh/_conv_highordermesh.py
cratch/mesh/_duplicate.py
cratch/mesh/_gen_geommesh.py
cratch/mesh/_gen_mesh.py
cratch/mesh/_gen_mesh_Q4.py
cratch/mesh/_gen_mesh_Q8.py
cratch/mesh/_gen_mesh_T3.py
cratch/mesh/_gen_mesh_T6.py
cratch/mesh/_geom_arc.py
cratch/mesh/_geom_ch.py
cratch/mesh/_geom_crack.py
cratch/mesh/_get_boundnodes.py
cratch/mesh/_get_elemsize.py
cratch/mesh/_get_related_nodes.py
cratch/mesh/_union.py
cratch/mesh/_union_interface.py
cratch/nn/__init__.py
cratch/nn/_class_data_loader.py
cratch/nn/_class_lcloss.py
cratch/nn/_class_mlp.py
cratch/nn/_get_weight_norm.py
cratch/nn/_make_datasets.py
cratch/nn/_model_init.py
cratch/plot/__init__.py
cratch/plot/_check_bc.py
cratch/plot/_cmap2dashedlines.py
cratch/plot/_cmap2list.py
cratch/plot/_cmap_discretize.py
cratch/plot/_plottools.py
cratch/plot/_rev_handleslabels.py
cratch/plot/_wireframe.py
cratch/utils/__init__.py
cratch/utils/_bctools.py
cratch/utils/_class_fem2d.py
cratch/utils/_conv_fast_bc.py
cratch/utils/_exactsolutions.py
cratch/utils/_matrixtools.py
cratch/utils/_mlstools.py
cratch/utils/_ptrtools.py
cratch/utils/_quadtools.py
cratch/utils/_shapefunctions.py
cratch/utils/_solvertools.py
cratch-0.0.5.dist-info/METADATA
cratch-0.0.5.dist-info/WHEEL
cratch-0.0.5.dist-info/licenses/LICENSE.txt
cratch-0.0.5.dist-info/RECORD
